flask_traffic/__init__.py
flask_traffic/_globals.py
flask_traffic/_helpers.py
flask_traffic/_log_policy.py
flask_traffic/_traffic.py
flask_traffic/stores/__init__.py
flask_traffic/stores/_protocols.py
flask_traffic/stores/csv.py
flask_traffic/stores/json.py
flask_traffic/stores/redis.py
flask_traffic/stores/sql.py
flask_traffic/stores/sql_orm.py
flask_traffic-0.8.2.dist-info/licenses/LICENSE.txt
flask_traffic-0.8.2.dist-info/WHEEL
flask_traffic-0.8.2.dist-info/METADATA
flask_traffic-0.8.2.dist-info/RECORD
