Metadata-Version: 2.4
Name: flask-traffic
Version: 0.8.2
Summary: Store and monitor site traffic.
Author-email: David Carmichael <david@uilix.com>
Requires-Python: >=3.9
Classifier: License :: OSI Approved :: MIT License
Classifier: Framework :: Flask
Classifier: Natural Language :: English
License-File: LICENSE.txt
Requires-Dist: Flask
Requires-Dist: flask-sqlalchemy ; extra == "flask-sqlalchemy"
Requires-Dist: redis ; extra == "redis"
Requires-Dist: sqlalchemy ; extra == "sqlalchemy"
Project-URL: Source, https://github.com/CheeseCake87/flask-traffic
Provides-Extra: flask-sqlalchemy
Provides-Extra: redis
Provides-Extra: sqlalchemy
